pipeline/__init__.py
pipeline/api_client.py
pipeline/cli.py
pipeline/config.py
pipeline/data_analyzer.py
pipeline/data_enricher.py
pipeline/pipeline.cfg
pipeline/pipeline.py
cartalyzer-0.1.1.dist-info/METADATA
cartalyzer-0.1.1.dist-info/WHEEL
cartalyzer-0.1.1.dist-info/entry_points.txt
cartalyzer-0.1.1.dist-info/RECORD
