Metadata-Version: 2.4
Name: cartalyzer
Version: 0.1.1
Summary: Fetch and analyze e-commerce cart data
License: MIT
Author: Ekene
Requires-Python: >=3.11
Classifier: License :: OSI Approved :: MIT License
Classifier: Programming Language :: Python :: 3
Classifier: Programming Language :: Python :: 3.11
Classifier: Programming Language :: Python :: 3.12
Classifier: Programming Language :: Python :: 3.13
Classifier: Programming Language :: Python :: 3.14
Requires-Dist: duckdb (>=1.4.0)
Requires-Dist: pandas (>=2.3.2)
Requires-Dist: requests (>=2.32.5)
